django_admin_performance_tools/__init__.py
django_admin_performance_tools/admin.py
django_admin_performance_tools/apps.py
django_admin_performance_tools/context_processors.py
django_admin_performance_tools/settings.py
django_admin_performance_tools/sites.py
django_admin_performance_tools/utils.py
django_admin_performance_tools/decorators/__init__.py
django_admin_performance_tools/decorators/action_max_selection_decorator.py
django_admin_performance_tools/filters/__init__.py
django_admin_performance_tools/filters/custom_titled_filter.py
django_admin_performance_tools/filters/filter_with_select_related.py
django_admin_performance_tools/intermediate_pages/__init__.py
django_admin_performance_tools/intermediate_pages/decorators/__init__.py
django_admin_performance_tools/intermediate_pages/decorators/intermediate_page_decorator.py
django_admin_performance_tools/intermediate_pages/forms/__init__.py
django_admin_performance_tools/intermediate_pages/forms/intermediate_page_form.py
django_admin_performance_tools/intermediate_pages/forms/intermediate_page_model_form.py
django_admin_performance_tools/migrations/__init__.py
django_admin_performance_tools/mixins/__init__.py
django_admin_performance_tools/mixins/change_select_related.py
django_admin_performance_tools/mixins/list_prefetch_related.py
django_admin_performance_tools/mixins/non_selection_actions.py
django_admin_performance_tools/mixins/readonly_select_related.py
django_admin_performance_tools/mixins/search_help_text.py
django_admin_performance_tools/permissions/__init__.py
django_admin_performance_tools/permissions/staff_permission_mixin.py
django_admin_performance_tools/quick_actions/__init__.py
django_admin_performance_tools/quick_actions/base_actions.py
django_admin_performance_tools/quick_actions/registry.py
django_admin_performance_tools/static/django_admin_performance_tools/css/style.css
django_admin_performance_tools/templates/admin/base_site.html
django_admin_performance_tools-1.0.1.dist-info/LICENSE
django_admin_performance_tools-1.0.1.dist-info/METADATA
django_admin_performance_tools-1.0.1.dist-info/WHEEL
django_admin_performance_tools-1.0.1.dist-info/top_level.txt
django_admin_performance_tools-1.0.1.dist-info/RECORD
