Metadata-Version: 2.1
Name: django-admin-performance-tools
Version: 1.0.1
Summary: Django Admin Performance Tools
Home-page: https://github.com/muhammedattif
Maintainer: Muhammed Atif
Maintainer-email: muhamedattif@gmail.com
License: MIT
Keywords: Django Admin
Classifier: Environment :: Web Environment
Classifier: Framework :: Django
Classifier: Framework :: Django :: 3.2
Classifier: Intended Audience :: Developers
Classifier: License :: OSI Approved :: MIT License
Classifier: Operating System :: OS Independent
Classifier: Programming Language :: Python
Classifier: Programming Language :: Python :: 3
Classifier: Programming Language :: Python :: 3 :: Only
Classifier: Programming Language :: Python :: 3.6
Classifier: Programming Language :: Python :: 3.7
Classifier: Programming Language :: Python :: 3.8
Requires-Python: >=3.8
License-File: LICENSE
Requires-Dist: Django >=3.2
